{
  "version": "7",
  "dialect": "sqlite",
  "entries": [
    {
      "idx": 0,
      "version": "6",
      "when": 1749615602242,
      "tag": "0000_clear_electro",
      "breakpoints": true
    },
    {
      "idx": 1,
      "version": "6",
      "when": 1749637439373,
      "tag": "0001_opposite_mongoose",
      "breakpoints": true
    },
    {
      "idx": 2,
      "version": "6",
      "when": 1749642459223,
      "tag": "0002_orange_union_jack",
      "breakpoints": true
    },
    {
      "idx": 3,
      "version": "6",
      "when": 1749692598527,
      "tag": "0003_orange_exiles",
      "breakpoints": true
    },
    {
      "idx": 4,
      "version": "6",
      "when": 1749693074861,
      "tag": "0004_nervous_ravenous",
      "breakpoints": true
    },
    {
      "idx": 5,
      "version": "6",
      "when": 1749693145407,
      "tag": "0005_great_gwen_stacy",
      "breakpoints": true
    },
    {
      "idx": 6,
      "version": "6",
      "when": 1749693266436,
      "tag": "0006_flimsy_carnage",
      "breakpoints": true
    },
    {
      "idx": 7,
      "version": "6",
      "when": 1749726024047,
      "tag": "0007_round_the_spike",
      "breakpoints": true
    },
    {
      "idx": 8,
      "version": "6",
      "when": 1749749459346,
      "tag": "0008_young_jocasta",
      "breakpoints": true
    },
    {
      "idx": 9,
      "version": "6",
      "when": 1749968404475,
      "tag": "0009_create-vector-embeddings",
      "breakpoints": true
    }
  ]
}